llm_contracts/__init__.py
llm_contracts/contracts.py
llm_contracts/cli/__init__.py
llm_contracts/cli/main.py
llm_contracts/core/__init__.py
llm_contracts/core/rules.py
llm_contracts/core/schema.py
llm_contracts/core/validator.py
llm_contracts/custom_validators/__init__.py
llm_contracts/custom_validators/base.py
llm_contracts/reports/__init__.py
llm_contracts/reports/html_generator.py
llm_contracts/reports/markdown_generator.py
llm_contracts/utils/__init__.py
llm_contracts/utils/yaml_loader.py
llm_contracts-1.0.0.dist-info/licenses/LICENSE
llm_contracts-1.0.0.dist-info/METADATA
llm_contracts-1.0.0.dist-info/WHEEL
llm_contracts-1.0.0.dist-info/entry_points.txt
llm_contracts-1.0.0.dist-info/top_level.txt
llm_contracts-1.0.0.dist-info/RECORD
