Metadata-Version: 2.4
Name: llm-contracts
Version: 1.0.0
Summary: LLM Output Validation, Linting, and Assertion Layer
Author-email: Mohamed Jama <mohamed.jama@gmail.com>
License: MIT
Project-URL: Homepage, https://github.com/Maxamed/llm-contract
Project-URL: Documentation, https://github.com/Maxamed/llm-contract#readme
Project-URL: Repository, https://github.com/Maxamed/llm-contract
Project-URL: Bug Tracker, https://github.com/Maxamed/llm-contract/issues
Keywords: llm,validation,linting,ai,schema,contracts
Classifier: Development Status :: 3 - Alpha
Classifier: Intended Audience :: Developers
Classifier: License :: OSI Approved :: MIT License
Classifier: Programming Language :: Python :: 3
Classifier: Programming Language :: Python :: 3.8
Classifier: Programming Language :: Python :: 3.9
Classifier: Programming Language :: Python :: 3.10
Classifier: Programming Language :: Python :: 3.11
Classifier: Programming Language :: Python :: 3.12
Classifier: Topic :: Software Development :: Libraries :: Python Modules
Classifier: Topic :: Software Development :: Testing
Requires-Python: >=3.8
License-File: LICENSE
Requires-Dist: pyyaml>=6.0
Requires-Dist: jsonschema>=4.17.0
Requires-Dist: click>=8.0.0
Provides-Extra: dev
Requires-Dist: pytest>=7.0.0; extra == "dev"
Requires-Dist: pytest-cov>=4.0.0; extra == "dev"
Requires-Dist: black>=23.0.0; extra == "dev"
Requires-Dist: isort>=5.12.0; extra == "dev"
Requires-Dist: flake8>=6.0.0; extra == "dev"
Requires-Dist: mypy>=1.0.0; extra == "dev"
Requires-Dist: pre-commit>=3.0.0; extra == "dev"
Requires-Dist: tox>=4.0.0; extra == "dev"
Dynamic: license-file
